{
  "APP_TITLE": "ESP Флешка",
  "HEADER_UPLOADING": "Загрузка",
  "BUTTON_TITLE_EXIT_DIR": "Выйти из директории",
  "BUTTON_TITLE_UPLOAD_FILE": "Загрузить файл",
  "BUTTON_FORCE_RECONNECT_USB": "Переподключить USB",
  "BUTTON_USB_SOFT_DISCONNECT": "Мягко отключить",
  "BUTTON_USB_SOFT_CONNECT": "Мягко подключить",
  "BUTTON_USB_HARD_DISCONNECT": "Жестко отключить",
  "BUTTON_USB_HARD_CONNECT": "Жестко подключить",
  "USB_STATUS_CONNECTED": "Connected",
  "USB_STATUS_PRESENT": "Present",
  "USB_STATUS_ON": "да",
  "USB_STATUS_OFF": "нет",
  "USB_STATUS_UNKNOWN": "неизвестно",
  "CONFIRM_DELETE_PREFIX": "Удалить",
  "ERROR_DELETE_FAILED": "Не удаось удалить",
  "ERROR_DOWNLOAD_FAILED": "Не удалось скачать",
  "ERROR_UPLOAD_FAILED": "Не удалось загрузить",
  "ERROR_USB_RECONNECT_FAILED": "Не удалось переподключить",
  "ERROR_USB_CONTROL_FAILED": "Не удалось выполнить USB-команду",
  "ERROR_API_STATUS": "Ошибка в запросе статуса",
  "ERROR_API_DELETE": "Ошибка в запросе на удаление",
  "ERROR_API_DOWNLOAD": "Ошибка в запросе на скачивание",
  "ERROR_API_USB_RECONNECT": "Ошибка в запросе на переподключение",
  "ERROR_API_USB_CONTROL": "Ошибка в запросе USB-команды",
  "ERROR_API_SHA256_NOT_LOADED": "sha256.min.js библиотека не загружена",
  "ERROR_API_UPLOAD": "Ошибка в запросе на загрузку",
  "ERROR_API_UPLOAD_COMMIT": "Ошибка проверки целостности",
  "ERROR_API_UPLOAD_ABORTED": "Загрузка отменена",
  "ERROR_API_HASH_FAILED": "Неудалось посчитать хещ",
  "UPLOAD_STATUS_INITIAL": "Инициализирован",
  "UPLOAD_STATUS_HASHING": "Хешируется",
  "UPLOAD_STATUS_UPLOADING": "Загружается",
  "UPLOAD_STATUS_UPLOADED": "Загружен",
  "UPLOAD_STATUS_FAILED": "Ошибка загрузки",
  "UPLOAD_STATUS_CHECKING": "Проверка",
  "UPLOAD_STATUS_CHECK_FAILED": "Не прошел првоерку",
  "UPLOAD_STATUS_SUCCESS": "Завершено",
  "UPLOAD_STATUS_ERROR": "Ошибка",
  "UPLOAD_STATUS_ABORTED": "Отменено"
}
